todo_agent/__init__.py
todo_agent/_version.py
todo_agent/main.py
todo_agent/core/__init__.py
todo_agent/core/conversation_manager.py
todo_agent/core/exceptions.py
todo_agent/core/todo_manager.py
todo_agent/infrastructure/__init__.py
todo_agent/infrastructure/calendar_utils.py
todo_agent/infrastructure/config.py
todo_agent/infrastructure/inference.py
todo_agent/infrastructure/llm_client.py
todo_agent/infrastructure/llm_client_factory.py
todo_agent/infrastructure/logger.py
todo_agent/infrastructure/math_solver.py
todo_agent/infrastructure/ollama_client.py
todo_agent/infrastructure/openrouter_client.py
todo_agent/infrastructure/todo_shell.py
todo_agent/infrastructure/token_counter.py
todo_agent/infrastructure/prompts/review_prompt.txt
todo_agent/infrastructure/prompts/system_prompt.txt
todo_agent/infrastructure/prompts/system_prompt_small.txt
todo_agent/interface/__init__.py
todo_agent/interface/cli.py
todo_agent/interface/formatters.py
todo_agent/interface/progress.py
todo_agent/interface/tools.py
todo_agent-0.3.12.dist-info/licenses/LICENSE
todo_agent-0.3.12.dist-info/METADATA
todo_agent-0.3.12.dist-info/WHEEL
todo_agent-0.3.12.dist-info/entry_points.txt
todo_agent-0.3.12.dist-info/top_level.txt
todo_agent-0.3.12.dist-info/RECORD
