Metadata-Version: 2.4
Name: todo-agent
Version: 0.3.12
Summary: A natural language interface for todo.sh task management
Author: codeprimate
Maintainer: codeprimate
License: GPL-3.0
Project-URL: Homepage, https://github.com/codeprimate/todo-agent
Project-URL: Documentation, https://github.com/codeprimate/todo-agent#readme
Project-URL: Repository, https://github.com/codeprimate/todo-agent
Project-URL: Bug Tracker, https://github.com/codeprimate/todo-agent/issues
Keywords: todo,task-management,llm,natural-language,cli
Classifier: Development Status :: 4 - Beta
Classifier: Intended Audience :: Developers
Classifier: Intended Audience :: End Users/Desktop
Classifier: Operating System :: OS Independent
Classifier: Programming Language :: Python :: 3
Classifier: Programming Language :: Python :: 3.10
Classifier: Programming Language :: Python :: 3.11
Classifier: Programming Language :: Python :: 3.12
Classifier: Topic :: Office/Business :: Scheduling
Classifier: Topic :: Software Development :: Libraries :: Python Modules
Classifier: Topic :: Text Processing :: Linguistic
Requires-Python: >=3.8
License-File: LICENSE
Requires-Dist: requests>=2.32.0
Requires-Dist: typing-extensions>=4.15.0
Requires-Dist: types-requests>=2.32.0
Requires-Dist: rich>=14.0.0
Requires-Dist: tiktoken>=0.11.0
Requires-Dist: sympy>=1.12
Provides-Extra: dev
Requires-Dist: ruff>=0.12.0; extra == "dev"
Requires-Dist: mypy>=1.17.0; extra == "dev"
Requires-Dist: pytest>=8.0.0; extra == "dev"
Requires-Dist: pytest-cov>=6.0.0; extra == "dev"
Requires-Dist: pre-commit>=4.0.0; extra == "dev"
Requires-Dist: bandit>=1.8.0; extra == "dev"
Requires-Dist: sphinx>=8.0.0; extra == "dev"
Requires-Dist: sphinx-rtd-theme>=3.0.0; extra == "dev"
Requires-Dist: radon>=6.0.0; extra == "dev"
Requires-Dist: xenon>=0.9.0; extra == "dev"
Requires-Dist: build>=1.2.0; extra == "dev"
Requires-Dist: twine>=6.0.0; extra == "dev"
Requires-Dist: setuptools_scm[toml]>=9.0.0; extra == "dev"
Dynamic: license-file
